augurs-0.8.0.dist-info/METADATA
augurs-0.8.0.dist-info/WHEEL
augurs-0.8.0.dist-info/licenses/LICENSE-APACHE
augurs-0.8.0.dist-info/licenses/LICENSE-MIT
augurs/__init__.py
augurs/__init__.pyi
augurs/py.typed
augurs/augurs.cp311-win_amd64.pyd
augurs-0.8.0.dist-info/RECORD
