Metadata-Version: 2.4
Name: augurs
Version: 0.8.0
Classifier: Programming Language :: Rust
Classifier: Programming Language :: Python :: Implementation :: CPython
Classifier: Programming Language :: Python :: Implementation :: PyPy
Requires-Dist: numpy
License-File: LICENSE-APACHE
License-File: LICENSE-MIT
Summary: Python bindings for the augurs time series library.
Keywords: analysis,forecasting,outlier-detection,time-series
Author: Ben Sully <ben.sully@grafana.com>
Author-email: Ben Sully <ben.sully@grafana.com>
License: MIT OR Apache-2.0
Requires-Python: >=3.9
Project-URL: Source Code, https://github.com/grafana/augurs
